MANIFEST.in
setup.py
prep_buddy.egg-info/PKG-INFO
prep_buddy.egg-info/SOURCES.txt
prep_buddy.egg-info/dependency_links.txt
prep_buddy.egg-info/requires.txt
prep_buddy.egg-info/top_level.txt
pyprepbuddy/__init__.py
pyprepbuddy/class_names.py
pyprepbuddy/package.py
pyprepbuddy/prep-buddy-0.5.0-jar-with-dependencies.jar
pyprepbuddy/serializer.py
pyprepbuddy/cleansers/__init__.py
pyprepbuddy/cleansers/imputation.py
pyprepbuddy/cluster/__init__.py
pyprepbuddy/cluster/cluster.py
pyprepbuddy/cluster/clustering_algorithm.py
pyprepbuddy/cluster/clusters.py
pyprepbuddy/cluster/text_facets.py
pyprepbuddy/exceptions/__init__.py
pyprepbuddy/exceptions/application_exception.py
pyprepbuddy/normalizers/__init__.py
pyprepbuddy/normalizers/normalizers.py
pyprepbuddy/rdds/__init__.py
pyprepbuddy/rdds/transformable_rdd.py
pyprepbuddy/smoothers/__init__.py
pyprepbuddy/smoothers/smoothing_algorithms.py
pyprepbuddy/utils/__init__.py
pyprepbuddy/utils/pivot_table.py
tests/__init__.py
tests/cluster/__init__.py
tests/cluster/cluster_test.py
tests/normalizers/__init__.py
tests/normalizers/noramalization_test.py
tests/rdds/__init__.py
tests/rdds/transformable_rdd_test.py
tests/smoothers/__init__.py
tests/smoothers/smoothers_test.py
tests/transformers/__init__.py
tests/transformers/merge_columns_test.py
tests/transformers/split_columns_test.py
utils/__init__.py
utils/python_test_case.py
utils/runCommand.py