Metadata-Version: 1.0
Name: prep-buddy
Version: 0.5.11
Summary: A library for cleaning, transforming and executing all other preparation tasks for large datasets on Apache Spark
Home-page: https://github.com/data-commons/prep-buddy
Author: data-commons
Author-email: data-commons-toolchain@googlegroups.com
License: Apache 2.0
Keywords: spark,cleaning,transforming,data,preparation
Platform: UNKNOWN
